README.rst
setup.py
twilight/__init__.py
twilight.egg-info/PKG-INFO
twilight.egg-info/SOURCES.txt
twilight.egg-info/dependency_links.txt
twilight.egg-info/entry_points.txt
twilight.egg-info/not-zip-safe
twilight.egg-info/requires.txt
twilight.egg-info/top_level.txt
twilight/cli/__init__.py
twilight/cli/arabic.py
twilight/cli/bbox.py
twilight/cli/countries.py
twilight/cli/datebin.py
twilight/cli/json2ttv2.py
twilight/cli/main.py
twilight/cli/sentiment.py
twilight/cli/user.py
twilight/cli/worker.py
twilight/lib/__init__.py
twilight/lib/accounts.py
twilight/lib/filesystem.py
twilight/lib/language.py
twilight/lib/logging.py
twilight/lib/tweets.py