Metadata-Version: 1.1
Name: twilight
Version: 0.3.10
Summary: Twitter (crawling) tools.
Home-page: http://github.com/chbrown/twilight
Author: Christopher Brown
Author-email: io@henrian.com
License: Copyright (c) 2011-2013 Christopher Brown
